pulumi_prefect/__init__.py
pulumi_prefect/_utilities.py
pulumi_prefect/account.py
pulumi_prefect/get_account.py
pulumi_prefect/get_account_member.py
pulumi_prefect/get_account_members.py
pulumi_prefect/get_account_role.py
pulumi_prefect/get_service_account.py
pulumi_prefect/get_team.py
pulumi_prefect/get_teams.py
pulumi_prefect/get_variable.py
pulumi_prefect/get_work_pool.py
pulumi_prefect/get_work_pools.py
pulumi_prefect/get_worker_metadata.py
pulumi_prefect/get_workspace.py
pulumi_prefect/get_workspace_role.py
pulumi_prefect/outputs.py
pulumi_prefect/provider.py
pulumi_prefect/pulumi-plugin.json
pulumi_prefect/py.typed
pulumi_prefect/service_account.py
pulumi_prefect/variable.py
pulumi_prefect/work_pool.py
pulumi_prefect/workspace.py
pulumi_prefect/workspace_access.py
pulumi_prefect/workspace_role.py
pulumi_prefect/config/__init__.py
pulumi_prefect/config/__init__.pyi
pulumi_prefect/config/vars.py
pulumi_prefect-0.1.4.dist-info/METADATA
pulumi_prefect-0.1.4.dist-info/WHEEL
pulumi_prefect-0.1.4.dist-info/top_level.txt
pulumi_prefect-0.1.4.dist-info/RECORD
