Metadata-Version: 2.1
Name: pulumi_prefect
Version: 0.1.4
Summary: A Pulumi package for creating and managing Prefect cloud resources.
License: Apache-2.0
Project-URL: Homepage, https://www.pulumi.com
Project-URL: Repository, https://github.com/ru5j4r0/pulumi-prefect
Keywords: prefect,prefect-cloud,category/cloud
Requires-Python: >=3.8
Requires-Dist: parver >=0.2.1
Requires-Dist: pulumi <4.0.0,>=3.0.0
Requires-Dist: semver >=2.8.1
